Metadata-Version: 2.1
Name: modelfun
Version: 0.0.1.4
Summary: A Python library for the Modelfun API
Home-page: https://github.com/modelfun/modelfun-python
Author: matrix
Author-email: brightmart@hotmail.com
License: UNKNOWN
Platform: UNKNOWN
Classifier: Programming Language :: Python :: 3
Classifier: License :: OSI Approved :: MIT License
Classifier: Operating System :: OS Independent
Requires-Python: >=3.6
License-File: LICENSE
